atlasapiclient/__init__.py
atlasapiclient/authentication.py
atlasapiclient/client.py
atlasapiclient/config.py
atlasapiclient/exceptions.py
atlasapiclient/utils.py
atlasapiclient/config_files/api_config_template.yaml
atlasapiclient-1.1.0.dist-info/licenses/LICENSE
atlasapiclient-1.1.0.dist-info/METADATA
atlasapiclient-1.1.0.dist-info/WHEEL
atlasapiclient-1.1.0.dist-info/top_level.txt
atlasapiclient-1.1.0.dist-info/RECORD
