Metadata-Version: 2.4
Name: atlasapiclient
Version: 1.1.0
Summary: API Client utility package for the ATLAS Transient Server
Author-email: Heloise Stevance <hfstevance@gmail.com>, Jack Leland <jack.leland@dtc.ox.ac.uk>, Ken Smith <ken.w.smith@gmail.com>
License: BSD-3-Clause
Keywords: astronomy,ATLAS API
Requires-Python: >=3.8
License-File: LICENSE
Requires-Dist: numpy
Requires-Dist: pandas
Requires-Dist: requests
Requires-Dist: tqdm
Requires-Dist: pyyaml
Requires-Dist: importlib-metadata; python_version < "3.9"
Provides-Extra: test
Requires-Dist: pytest; extra == "test"
Provides-Extra: docs
Requires-Dist: sphinx==7.4.7; extra == "docs"
Requires-Dist: sphinx_rtd_theme==3.0.2; extra == "docs"
Dynamic: license-file
